setup.py
qche/__init__.py
qche/qche.py
qche.egg-info/PKG-INFO
qche.egg-info/SOURCES.txt
qche.egg-info/dependency_links.txt
qche.egg-info/requires.txt
qche.egg-info/top_level.txt