Metadata-Version: 1.0
Name: qche
Version: 0.0.1
Summary: Filesystem-persisted cache with a dead simple interface
Home-page: http://github.com/rbaron/qche
Author: Raphael B.
Author-email: rbaron@rbaron.net
License: MIT
Keywords: cache filesystem
Platform: UNKNOWN
